{
    "list":[
        {
            "headline":"第一条标题",
            "date":"2018-05-25",
            "author":"唯一",
            "articletake":"第一条内容",
            "types":{
                "pic":"static/img/code.svg",
                "text":"HTML"
            },
            "tagsTitle":["html","算法"]
            
        },
        {
            "headline":"第二条标题",
            "date":"2018-05-28",
            "author":"xiao",
            "articletake":"第二条内容",
            "types":{
                "pic":"static/img/book.svg",
                "text":"书籍"
            },
            "tagsTitle":["html","算法","js"]
        },
        {
            "headline":"第三条标题",
            "date":"2018-05-29",
            "author":"xiao1",
            "articletake":"第三条内容",
            "types":{
                "pic":"static/img/book.svg",
                "text":"书籍"
            }
        },
        {
            "headline":"第四条标题",
            "date":"2018-05-28",
            "author":"xiao",
            "articletake":"第二条内容",
            "types":{
                "pic":"static/img/book.svg",
                "text":"书籍"
            },
            "tagsTitle":["html","算法","js"]
        },
        {
            "headline":"第五条标题",
            "date":"2018-05-28",
            "author":"xiao",
            "articletake":"第二条内容",
            "types":{
                "pic":"static/img/book.svg",
                "text":"书籍"
            },
            "tagsTitle":["html","算法","js"]
        },
        {
            "headline":"第六条标题",
            "date":"2018-05-28",
            "author":"xiao",
            "articletake":"第二条内容",
            "types":{
                "pic":"static/img/book.svg",
                "text":"书籍"
            },
            "tagsTitle":["html","算法","js"]
        },
        {
            "headline":"第七条标题",
            "date":"2018-05-28",
            "author":"xiao",
            "articletake":"第二条内容",
            "types":{
                "pic":"static/img/book.svg",
                "text":"书籍"
            },
            "tagsTitle":["html","算法","js"]
        }
    ]
}